[
	{
		"destination": "Baluran Sabana Park",
		"destinationId": "BLRN",
		"location": "Situbondo, East Java",
		"hotelGroup": "Camper",
		"name": "Baluran Camper Park Oke",
		"published": true,
		"unit": "person",
		"price": "750000",
		"minOrder": 3,
		"capacity": 20
	},
	{
		"destination": "Baluran Sabana Park",
		"destinationId": "BLRN",
		"location": "Situbondo, East Java",
		"hotelGroup": "Camper",
		"name": "Baluran Camper Park Oke Banget",
		"published": true,
		"unit": "person",
		"price": "750000",
		"minOrder": 3,
		"capacity": 20
	},
	{
		"destination": "Baluran Sabana Park",
		"destinationId": "BLRN",
		"location": "Situbondo, East Java",
		"hotelGroup": "Glamp Camp",
		"name": "Baluran Glamp Camp Rock",
		"published": true,
		"unit": "person",
		"price": "1000000",
		"minOrder": 3,
		"capacity": 20
	},
	{
		"destination": "Baluran Sabana Park",
		"destinationId": "BLRN",
		"location": "Situbondo, East Java",
		"hotelGroup": "Home Stay",
		"name": "Baluran Stay Home Stay",
		"published": true,
		"unit": "person",
		"price": "1000000",
		"minOrder": 3,
		"capacity": 20
	}
]